dsppy/__init__.py
dsppy/channel.py
dsppy/code.py
dsppy/quantize.py
dsppy/transform.py
dsppy/utils.py
dsppy-0.0.2.dist-info/licenses/LICENSE.md
dsppy-0.0.2.dist-info/METADATA
dsppy-0.0.2.dist-info/WHEEL
dsppy-0.0.2.dist-info/top_level.txt
dsppy-0.0.2.dist-info/RECORD
