Metadata-Version: 2.4
Name: dsppy
Version: 0.0.2
Summary: Digital signal processing for educational purposes.
Author: SiPBA Group
License-Expression: GPL-3.0-or-later
Project-URL: Homepage, https://github.com/SiPBA/dsppy/
Project-URL: Issues, https://github.com/SiPBA/dsppy/
Classifier: Programming Language :: Python :: 3
Classifier: Operating System :: OS Independent
Requires-Python: >=3.8
License-File: LICENSE.md
Requires-Dist: numpy
Requires-Dist: matplotlib
Requires-Dist: scipy
Requires-Dist: scikit-learn
Requires-Dist: networkx
Dynamic: license-file
